json_expand_o_matic/__init__.py
json_expand_o_matic/cli.py
json_expand_o_matic/contractor.py
json_expand_o_matic/expand_o_matic.py
json_expand_o_matic/expander.py
json_expand_o_matic/expansion_pool.py
json_expand_o_matic/expansion_zipper.py
json_expand_o_matic/leaf_node.py
json_expand_o_matic-0.2.4.dist-info/LICENSE.txt
json_expand_o_matic-0.2.4.dist-info/METADATA
json_expand_o_matic-0.2.4.dist-info/WHEEL
json_expand_o_matic-0.2.4.dist-info/entry_points.txt
json_expand_o_matic-0.2.4.dist-info/top_level.txt
json_expand_o_matic-0.2.4.dist-info/RECORD
