Metadata-Version: 2.1
Name: json-expand-o-matic
Version: 0.2.4
Summary: Expand a dict into a collection of subdirectories and json files or contract (un-expand) the output of expand() into a dict.
Home-page: https://github.com/jcejohnson/JsonExpandOMatic
Author: James Johnson
Author-email: jcejohnson@users.noreply.github.com
Keywords: json,jsonref
Classifier: Development Status :: 3 - Alpha
Classifier: Intended Audience :: Developers
Classifier: Topic :: Software Development :: Build Tools
Classifier: License :: OSI Approved :: MIT License
Classifier: Operating System :: OS Independent
Classifier: Programming Language :: Python :: 3.6
Classifier: Programming Language :: Python :: 3.7
Classifier: Programming Language :: Python :: 3.8
Classifier: Programming Language :: Python :: 3.9
Classifier: Programming Language :: Python :: Implementation :: PyPy
License-File: LICENSE.txt
